surf_forecast/__init__.py
surf_forecast/surf_forecast.py
surf_forecast-1.4.3.dist-info/LICENSE
surf_forecast-1.4.3.dist-info/METADATA
surf_forecast-1.4.3.dist-info/WHEEL
surf_forecast-1.4.3.dist-info/top_level.txt
surf_forecast-1.4.3.dist-info/RECORD
