Metadata-Version: 2.1
Name: surf-forecast
Version: 1.4.3
Summary: An api to fetch surf-forecast data
Home-page: https://github.com/dewittethomas/surf-forecast
Author: Thomas Dewitte
Author-email: thomasdewittecontact@gmail.com
License: MIT
Platform: UNKNOWN
Classifier: Development Status :: 5 - Production/Stable
Classifier: License :: OSI Approved :: MIT License
Classifier: Operating System :: OS Independent
Classifier: Programming Language :: Python :: 3
Requires-Python: >= 3.5
Requires-Dist: mechanize (>=0.4.5)
Requires-Dist: beautifulsoup4 (>=4.9.0)
